.project
.pydevproject
LICENSE
ez_setup.py
setup.cfg
setup.py
ndg/__init__.py
ndg/xacml/__init__.py
ndg/xacml/core/__init__.py
ndg/xacml/core/action.py
ndg/xacml/core/apply.py
ndg/xacml/core/attribute.py
ndg/xacml/core/attributedesignator.py
ndg/xacml/core/attributeselector.py
ndg/xacml/core/attributevalue.py
ndg/xacml/core/combinerparameter.py
ndg/xacml/core/condition.py
ndg/xacml/core/environment.py
ndg/xacml/core/expression.py
ndg/xacml/core/match.py
ndg/xacml/core/obligation.py
ndg/xacml/core/policy.py
ndg/xacml/core/policy_combining_alg.py
ndg/xacml/core/policybase.py
ndg/xacml/core/policydefaults.py
ndg/xacml/core/policyset.py
ndg/xacml/core/resource.py
ndg/xacml/core/rule.py
ndg/xacml/core/rule_combining_alg.py
ndg/xacml/core/subject.py
ndg/xacml/core/target.py
ndg/xacml/core/variabledefinition.py
ndg/xacml/core/variablereference.py
ndg/xacml/core/context/__init__.py
ndg/xacml/core/context/action.py
ndg/xacml/core/context/environment.py
ndg/xacml/core/context/exceptions.py
ndg/xacml/core/context/handler.py
ndg/xacml/core/context/handlerinterface.py
ndg/xacml/core/context/pap.py
ndg/xacml/core/context/pdp.py
ndg/xacml/core/context/pdpinterface.py
ndg/xacml/core/context/pip.py
ndg/xacml/core/context/pipinterface.py
ndg/xacml/core/context/request.py
ndg/xacml/core/context/resource.py
ndg/xacml/core/context/response.py
ndg/xacml/core/context/result.py
ndg/xacml/core/context/subject.py
ndg/xacml/core/documentation/Makefile
ndg/xacml/core/functions/__init__.py
ndg/xacml/core/functions/v1/__init__.py
ndg/xacml/core/functions/v1/and.py
ndg/xacml/core/functions/v1/at_least_one_member_of.py
ndg/xacml/core/functions/v1/bag.py
ndg/xacml/core/functions/v1/equal.py
ndg/xacml/core/functions/v1/match.py
ndg/xacml/core/functions/v1/not.py
ndg/xacml/core/functions/v1/one_and_only.py
ndg/xacml/core/functions/v1/regexp_match.py
ndg/xacml/core/functions/v1/round.py
ndg/xacml/core/functions/v2/__init__.py
ndg/xacml/core/functions/v2/concatenate.py
ndg_xacml.egg-info/PKG-INFO
ndg_xacml.egg-info/SOURCES.txt
ndg_xacml.egg-info/dependency_links.txt
ndg_xacml.egg-info/namespace_packages.txt
ndg_xacml.egg-info/not-zip-safe
ndg_xacml.egg-info/top_level.txt